{
  "utrecht": {
    "data-list": {
      "border-color": {
        "value": "{rvo.color.grijs-400}"
      },
      "border-width": {
        "value": "1px"
      },
      "margin-block-end": {
        "value": "0"
      },
      "margin-block-start": {
        "value": "0"
      },
      "item-key": {
        "border-inline-end-color": {
          "value": "{utrecht.data-list.border-color}"
        },
        "border-inline-end-width": {
          "value": "{utrecht.data-list.border-width}"
        },
        "color": {},
        "font-size": {},
        "font-weight": {
          "value": "{rvo.font-weight.bold}"
        },
        "line-height": {},
        "padding-block-end": {
          "value": "{rvo.space.xs}"
        },
        "padding-block-start": {
          "value": "{rvo.space.xs}"
        },
        "padding-inline-end": {
          "value": "{rvo.space.md}"
        },
        "padding-inline-start": {
          "value": "{rvo.space.md}"
        }
      },
      "item-value": {
        "color": {},
        "font-size": {},
        "line-height": {},
        "padding-block-end": {
          "value": "{rvo.space.xs}"
        },
        "padding-block-start": {
          "value": "{rvo.space.xs}"
        },
        "padding-inline-end": {
          "value": "{rvo.space.md}"
        },
        "padding-inline-start": {
          "value": "{rvo.space.md}"
        }
      },
      "rows": {
        "border-bottom-color": {
          "value": "{utrecht.data-list.border-color}"
        },
        "border-bottom-width": {
          "value": "{utrecht.data-list.border-width}"
        },
        "item": {
          "margin-block-start": {
            "value": "0"
          },
          "padding-inline-start": {
            "value": "{rvo.space.sm}"
          }
        },
        "item-value": {
          "margin-block-start": {
            "value": "0"
          }
        },
        "column": {
          "inline-size": {
            "value": "50%"
          },
          "min-inline-size": {
            "value": "25ch"
          }
        },
        "gap": {}
      }
    }
  }
}
